<?xml version="1.0" encoding="utf-8" ?>

<Apellidos xmlns="http://tempuri.org/DataSchema.xsd">
  <Apellido>Blanco</Apellido>
  <Apellido>Bello</Apellido>
  <Apellido>García</Apellido>
  <Apellido>Gutierrez</Apellido>
  <Apellido>Sánchez</Apellido>
  <Apellido>Pensado</Apellido>
  <Apellido>Barca</Apellido>
  <Apellido>Rodriguez</Apellido>
  <Apellido>González</Apellido>
  <Apellido>Costa</Apellido>
  <Apellido>Souto</Apellido>
  <Apellido>Mariño</Apellido>
  <Apellido>Fernández</Apellido>
  <Apellido>López</Apellido>
  <Apellido>Díaz</Apellido>
  <Apellido>Martínez</Apellido>
  <Apellido>Pérez</Apellido>
  <Apellido>Romero</Apellido>
  <Apellido>Álvarez</Apellido>
  <Apellido>Torres</Apellido>
  <Apellido>Ruiz</Apellido>
  <Apellido>Ramírez</Apellido>
  <Apellido>Suárez</Apellido>
  <Apellido>Moya</Apellido>
  <Apellido>Soto</Apellido>
</Apellidos>

